panel_precision_slider/__init__.py
panel_precision_slider/main.py
panel_precision_slider/py.typed
panel_precision_slider-0.1.0.dist-info/METADATA
panel_precision_slider-0.1.0.dist-info/WHEEL
panel_precision_slider-0.1.0.dist-info/licenses/LICENSE.txt
panel_precision_slider-0.1.0.dist-info/RECORD
