Metadata-Version: 2.3
Name: panel-precision-slider
Version: 0.1.0
Summary: A versatile slider with fine-tuned control, adjustable precision, and direct text input for exact values.
Project-URL: Homepage, https://github.com/panel-extensions/panel-precision-slider
Project-URL: Source, https://github.com/panel-extensions/panel-precision-slider
Author-email: Andrew Huang <ahuang@anaconda.com>
Maintainer-email: Andrew Huang <ahuang@anaconda.com>
License: BSD
Classifier: Development Status :: 5 - Production/Stable
Classifier: Intended Audience :: Developers
Classifier: Intended Audience :: Science/Research
Classifier: License :: OSI Approved :: BSD License
Classifier: Natural Language :: English
Classifier: Operating System :: OS Independent
Classifier: Programming Language :: Python :: 3
Classifier: Programming Language :: Python :: 3.10
Classifier: Programming Language :: Python :: 3.11
Classifier: Programming Language :: Python :: 3.12
Classifier: Programming Language :: Python :: 3.13
Classifier: Topic :: Scientific/Engineering
Classifier: Topic :: Software Development :: Libraries
Requires-Python: >=3.10
Requires-Dist: packaging
Requires-Dist: panel>=1.5.0
Provides-Extra: dev
Requires-Dist: mkdocs; extra == 'dev'
Requires-Dist: mkdocs-material; extra == 'dev'
Requires-Dist: mkdocstrings[python]; extra == 'dev'
Requires-Dist: pytest; extra == 'dev'
Requires-Dist: pytest-asyncio; extra == 'dev'
Requires-Dist: pytest-rerunfailures; extra == 'dev'
Requires-Dist: pytest-xdist; extra == 'dev'
Requires-Dist: watchfiles; extra == 'dev'
Provides-Extra: mypy
Requires-Dist: mypy; extra == 'mypy'
Requires-Dist: types-requests; extra == 'mypy'
Requires-Dist: typing-extensions; extra == 'mypy'
